MateGenOpenML/__init__.py
MateGenOpenML/assistant.py
MateGenOpenML-0.1.6.dist-info/METADATA
MateGenOpenML-0.1.6.dist-info/WHEEL
MateGenOpenML-0.1.6.dist-info/entry_points.txt
MateGenOpenML-0.1.6.dist-info/top_level.txt
MateGenOpenML-0.1.6.dist-info/RECORD
